UCTool/__init__.py
UCTool/main.py
UCTool/upload.py
UCTool_1.0-1.0.2.dist-info/METADATA
UCTool_1.0-1.0.2.dist-info/WHEEL
UCTool_1.0-1.0.2.dist-info/license.txt
UCTool_1.0-1.0.2.dist-info/top_level.txt
UCTool_1.0-1.0.2.dist-info/RECORD
