Metadata-Version: 2.1
Name: UCTool-1.0
Version: 1.0.2
Summary: UCTool-1.0
Author: xiejunwei
Author-email: xiejunwei@qq.com
License: MIT
Requires-Python: >=3
License-File: license.txt
Requires-Dist: pypinyin
Requires-Dist: opencv-python
